pyinvisiblewatermark/__init__.py
pyinvisiblewatermark/cli.py
pyinvisiblewatermark/core.py
pyinvisiblewatermark-0.1.1.dist-info/METADATA
pyinvisiblewatermark-0.1.1.dist-info/WHEEL
pyinvisiblewatermark-0.1.1.dist-info/entry_points.txt
pyinvisiblewatermark-0.1.1.dist-info/RECORD
