Metadata-Version: 2.1
Name: pyinvisiblewatermark
Version: 0.1.1
Summary: 
Home-page: https://github.com/DannyLee1991/invisiblewatermark
Author: lijianan
Author-email: lijianan@tezign.com
Requires-Python: >=3.9,<4.0
Classifier: Programming Language :: Python :: 3
Classifier: Programming Language :: Python :: 3.9
Classifier: Programming Language :: Python :: 3.10
Classifier: Programming Language :: Python :: 3.11
Requires-Dist: numpy (>=1.25.2,<2.0.0)
Requires-Dist: pillow (>=10.0.0,<11.0.0)
Requires-Dist: typer (>=0.9.0,<0.10.0)
Project-URL: Repository, https://github.com/DannyLee1991/invisiblewatermark
